dmg_reads/__init__.py
dmg_reads/__main__.py
dmg_reads/_version.py
dmg_reads/defaults.py
dmg_reads/extract.py
dmg_reads/lib.py
dmg_reads/utils.py
dmg_reads-1.0.5.dist-info/LICENSE
dmg_reads-1.0.5.dist-info/METADATA
dmg_reads-1.0.5.dist-info/WHEEL
dmg_reads-1.0.5.dist-info/entry_points.txt
dmg_reads-1.0.5.dist-info/top_level.txt
dmg_reads-1.0.5.dist-info/RECORD
